[
        [
                {
                        "direction": 2,
                        "route": "39A",
                        "start": {
                                "id": "1715",
                                "time": 1597321361
                        },
                        "stop": {
                                "id": "767",
                                "time": 1597323170
                        }
                }
        ],
        [
                {
                        "direction": 1,
                        "route": "145",
                        "start": {
                                "id": "1476",
                                "time": 1597321300
                        },
                        "stop": {
                                "id": "2007",
                                "time": 1597322876
                        }
                }
        ],
        [
                {
                        "direction": 2,
                        "route": "39",
                        "start": {
                                "id": "1715",
                                "time": 1597321026
                        },
                        "stop": {
                                "id": "1478",
                                "time": 1597321247
                        }
                },
                {
                        "direction": 1,
                        "route": "145",
                        "start": {
                                "id": "1478",
                                "time": 1597321457
                        },
                        "stop": {
                                "id": "2007",
                                "time": 1597322876
                        }
                }
        ],
        [
                {
                        "direction": 2,
                        "route": "39A",
                        "start": {
                                "id": "1715",
                                "time": 1597321961
                        },
                        "stop": {
                                "id": "767",
                                "time": 1597323770
                        }
                }
        ]
]